vrt_lss_packer/__init__.py
vrt_lss_packer/api_client.py
vrt_lss_packer/api_response.py
vrt_lss_packer/configuration.py
vrt_lss_packer/exceptions.py
vrt_lss_packer/py.typed
vrt_lss_packer/rest.py
vrt_lss_packer/api/__init__.py
vrt_lss_packer/api/pack_api.py
vrt_lss_packer/api/system_api.py
vrt_lss_packer/models/__init__.py
vrt_lss_packer/models/attribute.py
vrt_lss_packer/models/calculation_async_result.py
vrt_lss_packer/models/calculation_info.py
vrt_lss_packer/models/calculation_settings.py
vrt_lss_packer/models/calculation_state.py
vrt_lss_packer/models/calculation_status.py
vrt_lss_packer/models/check_result.py
vrt_lss_packer/models/coordinates.py
vrt_lss_packer/models/custom400_with_errors_and_warnings.py
vrt_lss_packer/models/dimensions.py
vrt_lss_packer/models/entity_error.py
vrt_lss_packer/models/entity_error_type.py
vrt_lss_packer/models/entity_path.py
vrt_lss_packer/models/entity_type.py
vrt_lss_packer/models/entity_warning.py
vrt_lss_packer/models/entity_warning_type.py
vrt_lss_packer/models/general402.py
vrt_lss_packer/models/general404.py
vrt_lss_packer/models/general404_detail.py
vrt_lss_packer/models/general429.py
vrt_lss_packer/models/general500.py
vrt_lss_packer/models/pack_result.py
vrt_lss_packer/models/pack_settings.py
vrt_lss_packer/models/pack_statistics.py
vrt_lss_packer/models/pack_task.py
vrt_lss_packer/models/package.py
vrt_lss_packer/models/package_layout.py
vrt_lss_packer/models/package_statistics.py
vrt_lss_packer/models/package_type.py
vrt_lss_packer/models/product.py
vrt_lss_packer/models/product_group_layout.py
vrt_lss_packer/models/product_layout.py
vrt_lss_packer/models/schema_error.py
vrt_lss_packer/models/service.py
vrt_lss_packer/models/tracedata.py
vrt_lss_packer/models/unpacked_items.py
vrt_lss_packer/models/validate_result.py
vrt_lss_packer/models/version_result.py
vrt_lss_packer-7.29.3120.dist-info/METADATA
vrt_lss_packer-7.29.3120.dist-info/WHEEL
vrt_lss_packer-7.29.3120.dist-info/top_level.txt
vrt_lss_packer-7.29.3120.dist-info/RECORD
