Metadata-Version: 2.2
Name: vrt_lss_packer
Version: 7.29.3120
Summary: VRt.Packer [PC]
Home-page: 
Author: Veeroute Support Team
Author-email: Veeroute Support Team <servicedesk@veeroute.com>
License: Proprietary
Project-URL: Repository, https://github.com/GIT_USER_ID/GIT_REPO_ID
Keywords: OpenAPI,VRt.Packer [PC]
Requires-Python: >=3.9
Requires-Dist: urllib3<3.0.0,>=2.1.0
Requires-Dist: python-dateutil>=2.8.2
Requires-Dist: pydantic>=2
Requires-Dist: typing-extensions>=4.7.1
Dynamic: author
